LICENSE
README.md
pyproject.toml
./src/__init__.py
./src/core/__init__.py
./src/core/cache/__init__.py
./src/core/chunk/__init__.py
./src/core/chunk/chunker.py
./src/core/chunk/langchain_chunker.py
./src/core/chunk/strategy_selector.py
./src/core/cli/__init__.py
./src/core/cli/__main__.py
./src/core/cli/app.py
./src/core/cli/main.py
./src/core/cli/commands/__init__.py
./src/core/cli/commands/batch.py
./src/core/cli/commands/batch_helpers.py
./src/core/cli/commands/chunk.py
./src/core/cli/commands/chunk_helpers.py
./src/core/cli/commands/eval.py
./src/core/cli/commands/info.py
./src/core/cli/commands/info_helpers.py
./src/core/cli/commands/ingest.py
./src/core/cli/commands/ingest_helpers.py
./src/core/cli/commands/retry.py
./src/core/cli/commands/retry_helpers.py
./src/core/cli/commands/search.py
./src/core/cli/commands/search_helpers.py
./src/core/cli/utils/__init__.py
./src/core/cli/utils/display.py
./src/core/cli/utils/output.py
./src/core/cli/utils/quality_check.py
./src/core/cli/utils/security.py
./src/core/cli/utils/validation.py
./src/core/config/__init__.py
./src/core/config/atlas_config.py
./src/core/config/defaults.py
./src/core/config/ocr_settings.py
./src/core/pipeline/__init__.py
./src/core/pipeline/history.py
./src/core/pipeline/interactive.py
./src/core/pipeline/retry.py
./src/core/pipeline/status.py
./src/core/storage/__init__.py
./src/core/storage/metadata_store.py
./src/core/storage/models.py
./src/core/vector/__init__.py
./src/core/vector/base.py
./src/core/vector/embeddings.py
./src/core/vector/qdrant_store.py
./src/workflows/__init__.py
./src/workflows/pipeline_with_metadata.py
./src/workflows/analyzer/__init__.py
./src/workflows/analyzer/complexity.py
./src/workflows/analyzer/document_type_classifier.py
./src/workflows/analyzer/image_quality_detector.py
./src/workflows/analyzer/ocr_quality_detector.py
./src/workflows/analyzer/profiler.py
./src/workflows/analyzer/schema_extractor.py
./src/workflows/analyzer/scientific_detector.py
ragctl.egg-info/PKG-INFO
ragctl.egg-info/SOURCES.txt
ragctl.egg-info/dependency_links.txt
ragctl.egg-info/entry_points.txt
ragctl.egg-info/requires.txt
ragctl.egg-info/top_level.txt
