Metadata-Version: 2.4
Name: ragctl
Version: 0.1.5
Summary: ragctl - Production-ready RAG toolkit with advanced OCR, semantic chunking, and intelligent document processing
Author-email: Horiz Data <sekkaahmed@gmail.com>
Maintainer-email: Horiz Data <sekkaahmed@gmail.com>
License-Expression: MIT
Project-URL: Homepage, https://github.com/datallmhub/ragctl
Project-URL: Documentation, https://github.com/datallmhub/ragctl/tree/main/docs
Project-URL: Repository, https://github.com/datallmhub/ragctl
Project-URL: Issues, https://github.com/datallmhub/ragctl/issues
Project-URL: Changelog, https://github.com/datallmhub/ragctl/blob/main/CHANGELOG.md
Keywords: rag,document-processing,ocr,chunking,nlp,machine-learning,embeddings,semantic-search
Classifier: Development Status :: 3 - Alpha
Classifier: Intended Audience :: Developers
Classifier: Intended Audience :: Science/Research
Classifier: Programming Language :: Python :: 3
Classifier: Programming Language :: Python :: 3.10
Classifier: Programming Language :: Python :: 3.11
Classifier: Programming Language :: Python :: 3.12
Classifier: Topic :: Scientific/Engineering :: Artificial Intelligence
Classifier: Topic :: Text Processing :: Linguistic
Classifier: Topic :: Software Development :: Libraries :: Python Modules
Requires-Python: <3.13,>=3.10
License-File: LICENSE
Requires-Dist: unstructured[docx,image,odt,pdf]>=0.10.0
Requires-Dist: python-docx>=1.0.0
Requires-Dist: beautifulsoup4>=4.12.0
Requires-Dist: pymupdf>=1.23.0
Requires-Dist: pdfplumber>=0.10.0
Requires-Dist: pdf2image>=1.16.0
Requires-Dist: langchain>=1.0.0
Requires-Dist: langchain-text-splitters>=1.0.0
Requires-Dist: langchain-community>=0.4.0
Requires-Dist: chonkie>=1.0.0
Requires-Dist: easyocr>=1.7.0
Requires-Dist: pytesseract>=0.3.10
Requires-Dist: pillow>=10.0.0
Requires-Dist: langdetect>=1.0.9
Requires-Dist: spacy>=3.7.0
Requires-Dist: tiktoken>=0.5.0
Requires-Dist: transformers>=4.44.0
Requires-Dist: datasets>=2.20.0
Requires-Dist: sentence-transformers>=2.2.0
Requires-Dist: scikit-learn>=1.5.0
Requires-Dist: torch>=2.2.0
Requires-Dist: joblib>=1.3.0
Requires-Dist: pandas>=2.0.0
Requires-Dist: numpy<2.0,>=1.26.0
Requires-Dist: scipy>=1.13.0
Requires-Dist: typer[all]>=0.12.0
Requires-Dist: rich>=13.0.0
Requires-Dist: qdrant-client>=1.7.0
Requires-Dist: langchain-qdrant>=0.1.0
Requires-Dist: psutil>=5.9.0
Requires-Dist: requests>=2.31.0
Provides-Extra: dev
Requires-Dist: pytest>=7.4.0; extra == "dev"
Requires-Dist: pytest-cov>=4.1.0; extra == "dev"
Requires-Dist: pytest-asyncio>=0.21.0; extra == "dev"
Requires-Dist: pytest-mock>=3.12.0; extra == "dev"
Requires-Dist: pytest-env>=1.1.0; extra == "dev"
Requires-Dist: black>=23.0.0; extra == "dev"
Requires-Dist: ruff>=0.1.0; extra == "dev"
Requires-Dist: flake8>=7.0.0; extra == "dev"
Requires-Dist: mypy>=1.7.0; extra == "dev"
Requires-Dist: isort>=5.12.0; extra == "dev"
Requires-Dist: safety>=3.0.0; extra == "dev"
Requires-Dist: bandit>=1.7.0; extra == "dev"
Requires-Dist: pre-commit>=3.5.0; extra == "dev"
Provides-Extra: ocr-advanced
Requires-Dist: easyocr>=1.7.0; extra == "ocr-advanced"
Requires-Dist: paddleocr>=2.7.0; extra == "ocr-advanced"
Provides-Extra: llm
Requires-Dist: openai>=1.0.0; extra == "llm"
Requires-Dist: anthropic>=0.7.0; extra == "llm"
Requires-Dist: ollama>=0.1.0; extra == "llm"
Dynamic: license-file
